<profile>
    <ReportVersion>
        <Version>2023.2</Version>
    </ReportVersion>
    <UserAssignments>
        <unit>ns</unit>
        <ProductFamily>virtex7</ProductFamily>
        <Part>xc7vx550t-ffg1927-1</Part>
        <TopModelName>ecal_cosmic_hls</TopModelName>
        <TargetClockPeriod>32.00</TargetClockPeriod>
        <ClockUncertainty>8.64</ClockUncertainty>
        <TargetInitiationInterval>1</TargetInitiationInterval>
        <FlowTarget>vivado</FlowTarget>
    </UserAssignments>
    <PerformanceEstimates>
        <PipelineType>yes(flp)</PipelineType>
        <SummaryOfTimingAnalysis>
            <unit>ns</unit>
            <EstimatedClockPeriod>20.335</EstimatedClockPeriod>
        </SummaryOfTimingAnalysis>
        <SummaryOfOverallLatency>
            <unit>clock cycles</unit>
            <Best-caseLatency>1</Best-caseLatency>
            <Average-caseLatency>1</Average-caseLatency>
            <Worst-caseLatency>1</Worst-caseLatency>
            <Best-caseRealTimeLatency>32.000 ns</Best-caseRealTimeLatency>
            <Average-caseRealTimeLatency>32.000 ns</Average-caseRealTimeLatency>
            <Worst-caseRealTimeLatency>32.000 ns</Worst-caseRealTimeLatency>
            <PipelineInitiationInterval>1</PipelineInitiationInterval>
            <PipelineDepth>2</PipelineDepth>
            <Interval-min>1</Interval-min>
            <Interval-max>1</Interval-max>
        </SummaryOfOverallLatency>
        <SummaryOfViolations>
            <IssueType>-</IssueType>
            <ViolationType>-</ViolationType>
            <SourceLocation>ecal_cosmic_hls.cpp:45</SourceLocation>
        </SummaryOfViolations>
    </PerformanceEstimates>
    <AreaEstimates>
        <Resources>
            <FF>92</FF>
            <LUT>3480</LUT>
            <BRAM_18K>0</BRAM_18K>
            <DSP>0</DSP>
            <URAM>0</URAM>
        </Resources>
        <AvailableResources>
            <BRAM_18K>2360</BRAM_18K>
            <DSP>2880</DSP>
            <FF>692800</FF>
            <LUT>346400</LUT>
            <URAM>0</URAM>
        </AvailableResources>
    </AreaEstimates>
    <InterfaceSummary>
        <RtlPorts>
            <name>ap_clk</name>
            <Object>ecal_cosmic_hls</Object>
            <Type>return value</Type>
            <Scope/>
            <IOProtocol>ap_ctrl_hs</IOProtocol>
            <IOConfig/>
            <Dir>in</Dir>
            <Bits>1</Bits>
            <Attribute>control</Attribute>
        </RtlPorts>
        <RtlPorts>
            <name>ap_rst</name>
            <Object>ecal_cosmic_hls</Object>
            <Type>return value</Type>
            <Scope/>
            <IOProtocol>ap_ctrl_hs</IOProtocol>
            <IOConfig/>
            <Dir>in</Dir>
            <Bits>1</Bits>
            <Attribute>control</Attribute>
        </RtlPorts>
        <RtlPorts>
            <name>ap_start</name>
            <Object>ecal_cosmic_hls</Object>
            <Type>return value</Type>
            <Scope/>
            <IOProtocol>ap_ctrl_hs</IOProtocol>
            <IOConfig/>
            <Dir>in</Dir>
            <Bits>1</Bits>
            <Attribute>control</Attribute>
        </RtlPorts>
        <RtlPorts>
            <name>ap_done</name>
            <Object>ecal_cosmic_hls</Object>
            <Type>return value</Type>
            <Scope/>
            <IOProtocol>ap_ctrl_hs</IOProtocol>
            <IOConfig/>
            <Dir>out</Dir>
            <Bits>1</Bits>
            <Attribute>control</Attribute>
        </RtlPorts>
        <RtlPorts>
            <name>ap_idle</name>
            <Object>ecal_cosmic_hls</Object>
            <Type>return value</Type>
            <Scope/>
            <IOProtocol>ap_ctrl_hs</IOProtocol>
            <IOConfig/>
            <Dir>out</Dir>
            <Bits>1</Bits>
            <Attribute>control</Attribute>
        </RtlPorts>
        <RtlPorts>
            <name>ap_ready</name>
            <Object>ecal_cosmic_hls</Object>
            <Type>return value</Type>
            <Scope/>
            <IOProtocol>ap_ctrl_hs</IOProtocol>
            <IOConfig/>
            <Dir>out</Dir>
            <Bits>1</Bits>
            <Attribute>control</Attribute>
        </RtlPorts>
        <RtlPorts>
            <name>s_fadc_hits_vxs_dout</name>
            <Object>s_fadc_hits_vxs</Object>
            <Type>pointer</Type>
            <Scope/>
            <IOProtocol>ap_fifo</IOProtocol>
            <IOConfig/>
            <Dir>in</Dir>
            <Bits>160</Bits>
            <Attribute>control</Attribute>
            <CType>int</CType>
        </RtlPorts>
        <RtlPorts>
            <name>s_fadc_hits_vxs_empty_n</name>
            <Object>s_fadc_hits_vxs</Object>
            <Type>pointer</Type>
            <Scope/>
            <IOProtocol>ap_fifo</IOProtocol>
            <IOConfig/>
            <Dir>in</Dir>
            <Bits>1</Bits>
            <Attribute>control</Attribute>
            <CType>int</CType>
        </RtlPorts>
        <RtlPorts>
            <name>s_fadc_hits_vxs_read</name>
            <Object>s_fadc_hits_vxs</Object>
            <Type>pointer</Type>
            <Scope/>
            <IOProtocol>ap_fifo</IOProtocol>
            <IOConfig/>
            <Dir>out</Dir>
            <Bits>1</Bits>
            <Attribute>control</Attribute>
            <CType>int</CType>
        </RtlPorts>
        <RtlPorts>
            <name>s_trigger_t_din</name>
            <Object>s_trigger_t</Object>
            <Type>pointer</Type>
            <Scope/>
            <IOProtocol>ap_fifo</IOProtocol>
            <IOConfig/>
            <Dir>out</Dir>
            <Bits>8</Bits>
            <Attribute>control</Attribute>
            <CType>int</CType>
        </RtlPorts>
        <RtlPorts>
            <name>s_trigger_t_full_n</name>
            <Object>s_trigger_t</Object>
            <Type>pointer</Type>
            <Scope/>
            <IOProtocol>ap_fifo</IOProtocol>
            <IOConfig/>
            <Dir>in</Dir>
            <Bits>1</Bits>
            <Attribute>control</Attribute>
            <CType>int</CType>
        </RtlPorts>
        <RtlPorts>
            <name>s_trigger_t_write</name>
            <Object>s_trigger_t</Object>
            <Type>pointer</Type>
            <Scope/>
            <IOProtocol>ap_fifo</IOProtocol>
            <IOConfig/>
            <Dir>out</Dir>
            <Bits>1</Bits>
            <Attribute>control</Attribute>
            <CType>int</CType>
        </RtlPorts>
        <RtlPorts>
            <name>hit_width</name>
            <Object>hit_width</Object>
            <Type>scalar</Type>
            <Scope/>
            <IOProtocol>ap_none</IOProtocol>
            <IOConfig/>
            <Dir>in</Dir>
            <Bits>3</Bits>
            <Attribute>data</Attribute>
            <CType>int</CType>
        </RtlPorts>
        <RtlPorts>
            <name>row_threshold</name>
            <Object>row_threshold</Object>
            <Type>scalar</Type>
            <Scope/>
            <IOProtocol>ap_none</IOProtocol>
            <IOConfig/>
            <Dir>in</Dir>
            <Bits>4</Bits>
            <Attribute>data</Attribute>
            <CType>int</CType>
        </RtlPorts>
    </InterfaceSummary>
    <RTLDesignHierarchy>
        <TopModule MAX_DEPTH="2">
            <ModuleName>ecal_cosmic_hls</ModuleName>
            <BindInstances>add_ln61_fu_529_p2 add_ln61_1_fu_591_p2 add_ln61_2_fu_643_p2 add_ln61_3_fu_697_p2 add_ln61_4_fu_749_p2 add_ln61_5_fu_801_p2 add_ln61_6_fu_853_p2 add_ln61_7_fu_959_p2 add_ln61_8_fu_1005_p2 add_ln61_9_fu_1051_p2 add_ln61_10_fu_1097_p2 add_ln61_11_fu_1143_p2 add_ln61_12_fu_1189_p2 add_ln61_13_fu_1235_p2 add_ln61_14_fu_1373_p2 add_ln61_15_fu_1419_p2 add_ln61_16_fu_1465_p2 add_ln61_17_fu_1511_p2 add_ln61_18_fu_1557_p2 add_ln61_19_fu_1603_p2 add_ln61_20_fu_1649_p2 add_ln61_21_fu_1787_p2 add_ln61_22_fu_1833_p2 add_ln61_23_fu_1879_p2 add_ln61_24_fu_1925_p2 add_ln61_25_fu_1971_p2 add_ln61_26_fu_2017_p2 add_ln61_27_fu_2063_p2 add_ln61_28_fu_2201_p2 add_ln61_29_fu_2247_p2 add_ln61_30_fu_2293_p2 add_ln61_31_fu_2339_p2 add_ln61_32_fu_2385_p2 add_ln61_33_fu_2431_p2 add_ln61_34_fu_2477_p2 add_ln61_35_fu_2615_p2 add_ln61_36_fu_2661_p2 add_ln61_37_fu_2707_p2 add_ln61_38_fu_2753_p2 add_ln61_39_fu_2799_p2 add_ln61_40_fu_2845_p2 add_ln61_41_fu_2891_p2 add_ln61_42_fu_3029_p2 add_ln61_43_fu_3075_p2 add_ln61_44_fu_3121_p2 add_ln61_45_fu_3167_p2 add_ln61_46_fu_3213_p2 add_ln61_47_fu_3259_p2 add_ln61_48_fu_3305_p2 add_ln61_49_fu_3443_p2 add_ln61_50_fu_3489_p2 add_ln61_51_fu_3535_p2 add_ln61_52_fu_3581_p2 add_ln61_53_fu_3627_p2 add_ln61_54_fu_3673_p2 add_ln61_55_fu_3719_p2 add_ln61_56_fu_3857_p2 add_ln61_57_fu_3903_p2 add_ln61_58_fu_3949_p2 add_ln61_59_fu_3995_p2 add_ln61_60_fu_4041_p2 add_ln61_61_fu_4087_p2 add_ln61_62_fu_4133_p2 add_ln61_63_fu_4271_p2 add_ln61_64_fu_4317_p2 add_ln61_65_fu_4363_p2 add_ln61_66_fu_4409_p2 add_ln61_67_fu_4455_p2 add_ln61_68_fu_4501_p2 add_ln61_69_fu_4547_p2</BindInstances>
        </TopModule>
    </RTLDesignHierarchy>
    <ModuleInformation>
        <Module>
            <Name>ecal_cosmic_hls</Name>
            <PerformanceEstimates>
                <SummaryOfTimingAnalysis>
                    <TargetClockPeriod>32.00</TargetClockPeriod>
                    <ClockUncertainty>8.64</ClockUncertainty>
                    <TargetInitiationInterval>1</TargetInitiationInterval>
                    <EstimatedClockPeriod>20.335</EstimatedClockPeriod>
                </SummaryOfTimingAnalysis>
                <SummaryOfOverallLatency>
                    <Best-caseLatency>1</Best-caseLatency>
                    <Average-caseLatency>1</Average-caseLatency>
                    <Worst-caseLatency>1</Worst-caseLatency>
                    <Best-caseRealTimeLatency>32.000 ns</Best-caseRealTimeLatency>
                    <Average-caseRealTimeLatency>32.000 ns</Average-caseRealTimeLatency>
                    <Worst-caseRealTimeLatency>32.000 ns</Worst-caseRealTimeLatency>
                    <PipelineInitiationInterval>1</PipelineInitiationInterval>
                    <PipelineDepth>2</PipelineDepth>
                    <PipelineType>yes(flp)</PipelineType>
                </SummaryOfOverallLatency>
                <SummaryOfViolations>
                    <IssueType>-</IssueType>
                    <ViolationType>-</ViolationType>
                    <SourceLocation>ecal_cosmic_hls.cpp:45</SourceLocation>
                </SummaryOfViolations>
            </PerformanceEstimates>
            <AreaEstimates>
                <Resources>
                    <FF>92</FF>
                    <AVAIL_FF>692800</AVAIL_FF>
                    <UTIL_FF>~0</UTIL_FF>
                    <LUT>3480</LUT>
                    <AVAIL_LUT>346400</AVAIL_LUT>
                    <UTIL_LUT>1</UTIL_LUT>
                    <BRAM_18K>0</BRAM_18K>
                    <AVAIL_BRAM>2360</AVAIL_BRAM>
                    <UTIL_BRAM>0</UTIL_BRAM>
                    <DSP>0</DSP>
                    <AVAIL_DSP>2880</AVAIL_DSP>
                    <UTIL_DSP>0</UTIL_DSP>
                    <URAM>0</URAM>
                    <AVAIL_URAM>0</AVAIL_URAM>
                    <UTIL_URAM>0</UTIL_URAM>
                </Resources>
            </AreaEstimates>
            <BindNodes>
                <BindNode BINDTYPE="op" BRAM="0" BUNDLEDNAME="" DISPNAME="bind_op add" DSP="0" ID="" IMPL="fabric" LATENCY="0" LOOP="" OPTYPE="add" PRAGMA="" RTLNAME="add_ln61_fu_529_p2" SOURCE="ecal_cosmic_hls.cpp:61" STORAGESUBTYPE="" URAM="0" VARIABLE="add_ln61"/>
                <BindNode BINDTYPE="op" BRAM="0" BUNDLEDNAME="" DISPNAME="bind_op add" DSP="0" ID="" IMPL="fabric" LATENCY="0" LOOP="" OPTYPE="add" PRAGMA="" RTLNAME="add_ln61_1_fu_591_p2" SOURCE="ecal_cosmic_hls.cpp:61" STORAGESUBTYPE="" URAM="0" VARIABLE="add_ln61_1"/>
                <BindNode BINDTYPE="op" BRAM="0" BUNDLEDNAME="" DISPNAME="bind_op add" DSP="0" ID="" IMPL="fabric" LATENCY="0" LOOP="" OPTYPE="add" PRAGMA="" RTLNAME="add_ln61_2_fu_643_p2" SOURCE="ecal_cosmic_hls.cpp:61" STORAGESUBTYPE="" URAM="0" VARIABLE="add_ln61_2"/>
                <BindNode BINDTYPE="op" BRAM="0" BUNDLEDNAME="" DISPNAME="bind_op add" DSP="0" ID="" IMPL="fabric" LATENCY="0" LOOP="" OPTYPE="add" PRAGMA="" RTLNAME="add_ln61_3_fu_697_p2" SOURCE="ecal_cosmic_hls.cpp:61" STORAGESUBTYPE="" URAM="0" VARIABLE="add_ln61_3"/>
                <BindNode BINDTYPE="op" BRAM="0" BUNDLEDNAME="" DISPNAME="bind_op add" DSP="0" ID="" IMPL="fabric" LATENCY="0" LOOP="" OPTYPE="add" PRAGMA="" RTLNAME="add_ln61_4_fu_749_p2" SOURCE="ecal_cosmic_hls.cpp:61" STORAGESUBTYPE="" URAM="0" VARIABLE="add_ln61_4"/>
                <BindNode BINDTYPE="op" BRAM="0" BUNDLEDNAME="" DISPNAME="bind_op add" DSP="0" ID="" IMPL="fabric" LATENCY="0" LOOP="" OPTYPE="add" PRAGMA="" RTLNAME="add_ln61_5_fu_801_p2" SOURCE="ecal_cosmic_hls.cpp:61" STORAGESUBTYPE="" URAM="0" VARIABLE="add_ln61_5"/>
                <BindNode BINDTYPE="op" BRAM="0" BUNDLEDNAME="" DISPNAME="bind_op add" DSP="0" ID="" IMPL="fabric" LATENCY="0" LOOP="" OPTYPE="add" PRAGMA="" RTLNAME="add_ln61_6_fu_853_p2" SOURCE="ecal_cosmic_hls.cpp:61" STORAGESUBTYPE="" URAM="0" VARIABLE="add_ln61_6"/>
                <BindNode BINDTYPE="op" BRAM="0" BUNDLEDNAME="" DISPNAME="bind_op add" DSP="0" ID="" IMPL="fabric" LATENCY="0" LOOP="" OPTYPE="add" PRAGMA="" RTLNAME="add_ln61_7_fu_959_p2" SOURCE="ecal_cosmic_hls.cpp:61" STORAGESUBTYPE="" URAM="0" VARIABLE="add_ln61_7"/>
                <BindNode BINDTYPE="op" BRAM="0" BUNDLEDNAME="" DISPNAME="bind_op add" DSP="0" ID="" IMPL="fabric" LATENCY="0" LOOP="" OPTYPE="add" PRAGMA="" RTLNAME="add_ln61_8_fu_1005_p2" SOURCE="ecal_cosmic_hls.cpp:61" STORAGESUBTYPE="" URAM="0" VARIABLE="add_ln61_8"/>
                <BindNode BINDTYPE="op" BRAM="0" BUNDLEDNAME="" DISPNAME="bind_op add" DSP="0" ID="" IMPL="fabric" LATENCY="0" LOOP="" OPTYPE="add" PRAGMA="" RTLNAME="add_ln61_9_fu_1051_p2" SOURCE="ecal_cosmic_hls.cpp:61" STORAGESUBTYPE="" URAM="0" VARIABLE="add_ln61_9"/>
                <BindNode BINDTYPE="op" BRAM="0" BUNDLEDNAME="" DISPNAME="bind_op add" DSP="0" ID="" IMPL="fabric" LATENCY="0" LOOP="" OPTYPE="add" PRAGMA="" RTLNAME="add_ln61_10_fu_1097_p2" SOURCE="ecal_cosmic_hls.cpp:61" STORAGESUBTYPE="" URAM="0" VARIABLE="add_ln61_10"/>
                <BindNode BINDTYPE="op" BRAM="0" BUNDLEDNAME="" DISPNAME="bind_op add" DSP="0" ID="" IMPL="fabric" LATENCY="0" LOOP="" OPTYPE="add" PRAGMA="" RTLNAME="add_ln61_11_fu_1143_p2" SOURCE="ecal_cosmic_hls.cpp:61" STORAGESUBTYPE="" URAM="0" VARIABLE="add_ln61_11"/>
                <BindNode BINDTYPE="op" BRAM="0" BUNDLEDNAME="" DISPNAME="bind_op add" DSP="0" ID="" IMPL="fabric" LATENCY="0" LOOP="" OPTYPE="add" PRAGMA="" RTLNAME="add_ln61_12_fu_1189_p2" SOURCE="ecal_cosmic_hls.cpp:61" STORAGESUBTYPE="" URAM="0" VARIABLE="add_ln61_12"/>
                <BindNode BINDTYPE="op" BRAM="0" BUNDLEDNAME="" DISPNAME="bind_op add" DSP="0" ID="" IMPL="fabric" LATENCY="0" LOOP="" OPTYPE="add" PRAGMA="" RTLNAME="add_ln61_13_fu_1235_p2" SOURCE="ecal_cosmic_hls.cpp:61" STORAGESUBTYPE="" URAM="0" VARIABLE="add_ln61_13"/>
                <BindNode BINDTYPE="op" BRAM="0" BUNDLEDNAME="" DISPNAME="bind_op add" DSP="0" ID="" IMPL="fabric" LATENCY="0" LOOP="" OPTYPE="add" PRAGMA="" RTLNAME="add_ln61_14_fu_1373_p2" SOURCE="ecal_cosmic_hls.cpp:61" STORAGESUBTYPE="" URAM="0" VARIABLE="add_ln61_14"/>
                <BindNode BINDTYPE="op" BRAM="0" BUNDLEDNAME="" DISPNAME="bind_op add" DSP="0" ID="" IMPL="fabric" LATENCY="0" LOOP="" OPTYPE="add" PRAGMA="" RTLNAME="add_ln61_15_fu_1419_p2" SOURCE="ecal_cosmic_hls.cpp:61" STORAGESUBTYPE="" URAM="0" VARIABLE="add_ln61_15"/>
                <BindNode BINDTYPE="op" BRAM="0" BUNDLEDNAME="" DISPNAME="bind_op add" DSP="0" ID="" IMPL="fabric" LATENCY="0" LOOP="" OPTYPE="add" PRAGMA="" RTLNAME="add_ln61_16_fu_1465_p2" SOURCE="ecal_cosmic_hls.cpp:61" STORAGESUBTYPE="" URAM="0" VARIABLE="add_ln61_16"/>
                <BindNode BINDTYPE="op" BRAM="0" BUNDLEDNAME="" DISPNAME="bind_op add" DSP="0" ID="" IMPL="fabric" LATENCY="0" LOOP="" OPTYPE="add" PRAGMA="" RTLNAME="add_ln61_17_fu_1511_p2" SOURCE="ecal_cosmic_hls.cpp:61" STORAGESUBTYPE="" URAM="0" VARIABLE="add_ln61_17"/>
                <BindNode BINDTYPE="op" BRAM="0" BUNDLEDNAME="" DISPNAME="bind_op add" DSP="0" ID="" IMPL="fabric" LATENCY="0" LOOP="" OPTYPE="add" PRAGMA="" RTLNAME="add_ln61_18_fu_1557_p2" SOURCE="ecal_cosmic_hls.cpp:61" STORAGESUBTYPE="" URAM="0" VARIABLE="add_ln61_18"/>
                <BindNode BINDTYPE="op" BRAM="0" BUNDLEDNAME="" DISPNAME="bind_op add" DSP="0" ID="" IMPL="fabric" LATENCY="0" LOOP="" OPTYPE="add" PRAGMA="" RTLNAME="add_ln61_19_fu_1603_p2" SOURCE="ecal_cosmic_hls.cpp:61" STORAGESUBTYPE="" URAM="0" VARIABLE="add_ln61_19"/>
                <BindNode BINDTYPE="op" BRAM="0" BUNDLEDNAME="" DISPNAME="bind_op add" DSP="0" ID="" IMPL="fabric" LATENCY="0" LOOP="" OPTYPE="add" PRAGMA="" RTLNAME="add_ln61_20_fu_1649_p2" SOURCE="ecal_cosmic_hls.cpp:61" STORAGESUBTYPE="" URAM="0" VARIABLE="add_ln61_20"/>
                <BindNode BINDTYPE="op" BRAM="0" BUNDLEDNAME="" DISPNAME="bind_op add" DSP="0" ID="" IMPL="fabric" LATENCY="0" LOOP="" OPTYPE="add" PRAGMA="" RTLNAME="add_ln61_21_fu_1787_p2" SOURCE="ecal_cosmic_hls.cpp:61" STORAGESUBTYPE="" URAM="0" VARIABLE="add_ln61_21"/>
                <BindNode BINDTYPE="op" BRAM="0" BUNDLEDNAME="" DISPNAME="bind_op add" DSP="0" ID="" IMPL="fabric" LATENCY="0" LOOP="" OPTYPE="add" PRAGMA="" RTLNAME="add_ln61_22_fu_1833_p2" SOURCE="ecal_cosmic_hls.cpp:61" STORAGESUBTYPE="" URAM="0" VARIABLE="add_ln61_22"/>
                <BindNode BINDTYPE="op" BRAM="0" BUNDLEDNAME="" DISPNAME="bind_op add" DSP="0" ID="" IMPL="fabric" LATENCY="0" LOOP="" OPTYPE="add" PRAGMA="" RTLNAME="add_ln61_23_fu_1879_p2" SOURCE="ecal_cosmic_hls.cpp:61" STORAGESUBTYPE="" URAM="0" VARIABLE="add_ln61_23"/>
                <BindNode BINDTYPE="op" BRAM="0" BUNDLEDNAME="" DISPNAME="bind_op add" DSP="0" ID="" IMPL="fabric" LATENCY="0" LOOP="" OPTYPE="add" PRAGMA="" RTLNAME="add_ln61_24_fu_1925_p2" SOURCE="ecal_cosmic_hls.cpp:61" STORAGESUBTYPE="" URAM="0" VARIABLE="add_ln61_24"/>
                <BindNode BINDTYPE="op" BRAM="0" BUNDLEDNAME="" DISPNAME="bind_op add" DSP="0" ID="" IMPL="fabric" LATENCY="0" LOOP="" OPTYPE="add" PRAGMA="" RTLNAME="add_ln61_25_fu_1971_p2" SOURCE="ecal_cosmic_hls.cpp:61" STORAGESUBTYPE="" URAM="0" VARIABLE="add_ln61_25"/>
                <BindNode BINDTYPE="op" BRAM="0" BUNDLEDNAME="" DISPNAME="bind_op add" DSP="0" ID="" IMPL="fabric" LATENCY="0" LOOP="" OPTYPE="add" PRAGMA="" RTLNAME="add_ln61_26_fu_2017_p2" SOURCE="ecal_cosmic_hls.cpp:61" STORAGESUBTYPE="" URAM="0" VARIABLE="add_ln61_26"/>
                <BindNode BINDTYPE="op" BRAM="0" BUNDLEDNAME="" DISPNAME="bind_op add" DSP="0" ID="" IMPL="fabric" LATENCY="0" LOOP="" OPTYPE="add" PRAGMA="" RTLNAME="add_ln61_27_fu_2063_p2" SOURCE="ecal_cosmic_hls.cpp:61" STORAGESUBTYPE="" URAM="0" VARIABLE="add_ln61_27"/>
                <BindNode BINDTYPE="op" BRAM="0" BUNDLEDNAME="" DISPNAME="bind_op add" DSP="0" ID="" IMPL="fabric" LATENCY="0" LOOP="" OPTYPE="add" PRAGMA="" RTLNAME="add_ln61_28_fu_2201_p2" SOURCE="ecal_cosmic_hls.cpp:61" STORAGESUBTYPE="" URAM="0" VARIABLE="add_ln61_28"/>
                <BindNode BINDTYPE="op" BRAM="0" BUNDLEDNAME="" DISPNAME="bind_op add" DSP="0" ID="" IMPL="fabric" LATENCY="0" LOOP="" OPTYPE="add" PRAGMA="" RTLNAME="add_ln61_29_fu_2247_p2" SOURCE="ecal_cosmic_hls.cpp:61" STORAGESUBTYPE="" URAM="0" VARIABLE="add_ln61_29"/>
                <BindNode BINDTYPE="op" BRAM="0" BUNDLEDNAME="" DISPNAME="bind_op add" DSP="0" ID="" IMPL="fabric" LATENCY="0" LOOP="" OPTYPE="add" PRAGMA="" RTLNAME="add_ln61_30_fu_2293_p2" SOURCE="ecal_cosmic_hls.cpp:61" STORAGESUBTYPE="" URAM="0" VARIABLE="add_ln61_30"/>
                <BindNode BINDTYPE="op" BRAM="0" BUNDLEDNAME="" DISPNAME="bind_op add" DSP="0" ID="" IMPL="fabric" LATENCY="0" LOOP="" OPTYPE="add" PRAGMA="" RTLNAME="add_ln61_31_fu_2339_p2" SOURCE="ecal_cosmic_hls.cpp:61" STORAGESUBTYPE="" URAM="0" VARIABLE="add_ln61_31"/>
                <BindNode BINDTYPE="op" BRAM="0" BUNDLEDNAME="" DISPNAME="bind_op add" DSP="0" ID="" IMPL="fabric" LATENCY="0" LOOP="" OPTYPE="add" PRAGMA="" RTLNAME="add_ln61_32_fu_2385_p2" SOURCE="ecal_cosmic_hls.cpp:61" STORAGESUBTYPE="" URAM="0" VARIABLE="add_ln61_32"/>
                <BindNode BINDTYPE="op" BRAM="0" BUNDLEDNAME="" DISPNAME="bind_op add" DSP="0" ID="" IMPL="fabric" LATENCY="0" LOOP="" OPTYPE="add" PRAGMA="" RTLNAME="add_ln61_33_fu_2431_p2" SOURCE="ecal_cosmic_hls.cpp:61" STORAGESUBTYPE="" URAM="0" VARIABLE="add_ln61_33"/>
                <BindNode BINDTYPE="op" BRAM="0" BUNDLEDNAME="" DISPNAME="bind_op add" DSP="0" ID="" IMPL="fabric" LATENCY="0" LOOP="" OPTYPE="add" PRAGMA="" RTLNAME="add_ln61_34_fu_2477_p2" SOURCE="ecal_cosmic_hls.cpp:61" STORAGESUBTYPE="" URAM="0" VARIABLE="add_ln61_34"/>
                <BindNode BINDTYPE="op" BRAM="0" BUNDLEDNAME="" DISPNAME="bind_op add" DSP="0" ID="" IMPL="fabric" LATENCY="0" LOOP="" OPTYPE="add" PRAGMA="" RTLNAME="add_ln61_35_fu_2615_p2" SOURCE="ecal_cosmic_hls.cpp:61" STORAGESUBTYPE="" URAM="0" VARIABLE="add_ln61_35"/>
                <BindNode BINDTYPE="op" BRAM="0" BUNDLEDNAME="" DISPNAME="bind_op add" DSP="0" ID="" IMPL="fabric" LATENCY="0" LOOP="" OPTYPE="add" PRAGMA="" RTLNAME="add_ln61_36_fu_2661_p2" SOURCE="ecal_cosmic_hls.cpp:61" STORAGESUBTYPE="" URAM="0" VARIABLE="add_ln61_36"/>
                <BindNode BINDTYPE="op" BRAM="0" BUNDLEDNAME="" DISPNAME="bind_op add" DSP="0" ID="" IMPL="fabric" LATENCY="0" LOOP="" OPTYPE="add" PRAGMA="" RTLNAME="add_ln61_37_fu_2707_p2" SOURCE="ecal_cosmic_hls.cpp:61" STORAGESUBTYPE="" URAM="0" VARIABLE="add_ln61_37"/>
                <BindNode BINDTYPE="op" BRAM="0" BUNDLEDNAME="" DISPNAME="bind_op add" DSP="0" ID="" IMPL="fabric" LATENCY="0" LOOP="" OPTYPE="add" PRAGMA="" RTLNAME="add_ln61_38_fu_2753_p2" SOURCE="ecal_cosmic_hls.cpp:61" STORAGESUBTYPE="" URAM="0" VARIABLE="add_ln61_38"/>
                <BindNode BINDTYPE="op" BRAM="0" BUNDLEDNAME="" DISPNAME="bind_op add" DSP="0" ID="" IMPL="fabric" LATENCY="0" LOOP="" OPTYPE="add" PRAGMA="" RTLNAME="add_ln61_39_fu_2799_p2" SOURCE="ecal_cosmic_hls.cpp:61" STORAGESUBTYPE="" URAM="0" VARIABLE="add_ln61_39"/>
                <BindNode BINDTYPE="op" BRAM="0" BUNDLEDNAME="" DISPNAME="bind_op add" DSP="0" ID="" IMPL="fabric" LATENCY="0" LOOP="" OPTYPE="add" PRAGMA="" RTLNAME="add_ln61_40_fu_2845_p2" SOURCE="ecal_cosmic_hls.cpp:61" STORAGESUBTYPE="" URAM="0" VARIABLE="add_ln61_40"/>
                <BindNode BINDTYPE="op" BRAM="0" BUNDLEDNAME="" DISPNAME="bind_op add" DSP="0" ID="" IMPL="fabric" LATENCY="0" LOOP="" OPTYPE="add" PRAGMA="" RTLNAME="add_ln61_41_fu_2891_p2" SOURCE="ecal_cosmic_hls.cpp:61" STORAGESUBTYPE="" URAM="0" VARIABLE="add_ln61_41"/>
                <BindNode BINDTYPE="op" BRAM="0" BUNDLEDNAME="" DISPNAME="bind_op add" DSP="0" ID="" IMPL="fabric" LATENCY="0" LOOP="" OPTYPE="add" PRAGMA="" RTLNAME="add_ln61_42_fu_3029_p2" SOURCE="ecal_cosmic_hls.cpp:61" STORAGESUBTYPE="" URAM="0" VARIABLE="add_ln61_42"/>
                <BindNode BINDTYPE="op" BRAM="0" BUNDLEDNAME="" DISPNAME="bind_op add" DSP="0" ID="" IMPL="fabric" LATENCY="0" LOOP="" OPTYPE="add" PRAGMA="" RTLNAME="add_ln61_43_fu_3075_p2" SOURCE="ecal_cosmic_hls.cpp:61" STORAGESUBTYPE="" URAM="0" VARIABLE="add_ln61_43"/>
                <BindNode BINDTYPE="op" BRAM="0" BUNDLEDNAME="" DISPNAME="bind_op add" DSP="0" ID="" IMPL="fabric" LATENCY="0" LOOP="" OPTYPE="add" PRAGMA="" RTLNAME="add_ln61_44_fu_3121_p2" SOURCE="ecal_cosmic_hls.cpp:61" STORAGESUBTYPE="" URAM="0" VARIABLE="add_ln61_44"/>
                <BindNode BINDTYPE="op" BRAM="0" BUNDLEDNAME="" DISPNAME="bind_op add" DSP="0" ID="" IMPL="fabric" LATENCY="0" LOOP="" OPTYPE="add" PRAGMA="" RTLNAME="add_ln61_45_fu_3167_p2" SOURCE="ecal_cosmic_hls.cpp:61" STORAGESUBTYPE="" URAM="0" VARIABLE="add_ln61_45"/>
                <BindNode BINDTYPE="op" BRAM="0" BUNDLEDNAME="" DISPNAME="bind_op add" DSP="0" ID="" IMPL="fabric" LATENCY="0" LOOP="" OPTYPE="add" PRAGMA="" RTLNAME="add_ln61_46_fu_3213_p2" SOURCE="ecal_cosmic_hls.cpp:61" STORAGESUBTYPE="" URAM="0" VARIABLE="add_ln61_46"/>
                <BindNode BINDTYPE="op" BRAM="0" BUNDLEDNAME="" DISPNAME="bind_op add" DSP="0" ID="" IMPL="fabric" LATENCY="0" LOOP="" OPTYPE="add" PRAGMA="" RTLNAME="add_ln61_47_fu_3259_p2" SOURCE="ecal_cosmic_hls.cpp:61" STORAGESUBTYPE="" URAM="0" VARIABLE="add_ln61_47"/>
                <BindNode BINDTYPE="op" BRAM="0" BUNDLEDNAME="" DISPNAME="bind_op add" DSP="0" ID="" IMPL="fabric" LATENCY="0" LOOP="" OPTYPE="add" PRAGMA="" RTLNAME="add_ln61_48_fu_3305_p2" SOURCE="ecal_cosmic_hls.cpp:61" STORAGESUBTYPE="" URAM="0" VARIABLE="add_ln61_48"/>
                <BindNode BINDTYPE="op" BRAM="0" BUNDLEDNAME="" DISPNAME="bind_op add" DSP="0" ID="" IMPL="fabric" LATENCY="0" LOOP="" OPTYPE="add" PRAGMA="" RTLNAME="add_ln61_49_fu_3443_p2" SOURCE="ecal_cosmic_hls.cpp:61" STORAGESUBTYPE="" URAM="0" VARIABLE="add_ln61_49"/>
                <BindNode BINDTYPE="op" BRAM="0" BUNDLEDNAME="" DISPNAME="bind_op add" DSP="0" ID="" IMPL="fabric" LATENCY="0" LOOP="" OPTYPE="add" PRAGMA="" RTLNAME="add_ln61_50_fu_3489_p2" SOURCE="ecal_cosmic_hls.cpp:61" STORAGESUBTYPE="" URAM="0" VARIABLE="add_ln61_50"/>
                <BindNode BINDTYPE="op" BRAM="0" BUNDLEDNAME="" DISPNAME="bind_op add" DSP="0" ID="" IMPL="fabric" LATENCY="0" LOOP="" OPTYPE="add" PRAGMA="" RTLNAME="add_ln61_51_fu_3535_p2" SOURCE="ecal_cosmic_hls.cpp:61" STORAGESUBTYPE="" URAM="0" VARIABLE="add_ln61_51"/>
                <BindNode BINDTYPE="op" BRAM="0" BUNDLEDNAME="" DISPNAME="bind_op add" DSP="0" ID="" IMPL="fabric" LATENCY="0" LOOP="" OPTYPE="add" PRAGMA="" RTLNAME="add_ln61_52_fu_3581_p2" SOURCE="ecal_cosmic_hls.cpp:61" STORAGESUBTYPE="" URAM="0" VARIABLE="add_ln61_52"/>
                <BindNode BINDTYPE="op" BRAM="0" BUNDLEDNAME="" DISPNAME="bind_op add" DSP="0" ID="" IMPL="fabric" LATENCY="0" LOOP="" OPTYPE="add" PRAGMA="" RTLNAME="add_ln61_53_fu_3627_p2" SOURCE="ecal_cosmic_hls.cpp:61" STORAGESUBTYPE="" URAM="0" VARIABLE="add_ln61_53"/>
                <BindNode BINDTYPE="op" BRAM="0" BUNDLEDNAME="" DISPNAME="bind_op add" DSP="0" ID="" IMPL="fabric" LATENCY="0" LOOP="" OPTYPE="add" PRAGMA="" RTLNAME="add_ln61_54_fu_3673_p2" SOURCE="ecal_cosmic_hls.cpp:61" STORAGESUBTYPE="" URAM="0" VARIABLE="add_ln61_54"/>
                <BindNode BINDTYPE="op" BRAM="0" BUNDLEDNAME="" DISPNAME="bind_op add" DSP="0" ID="" IMPL="fabric" LATENCY="0" LOOP="" OPTYPE="add" PRAGMA="" RTLNAME="add_ln61_55_fu_3719_p2" SOURCE="ecal_cosmic_hls.cpp:61" STORAGESUBTYPE="" URAM="0" VARIABLE="add_ln61_55"/>
                <BindNode BINDTYPE="op" BRAM="0" BUNDLEDNAME="" DISPNAME="bind_op add" DSP="0" ID="" IMPL="fabric" LATENCY="0" LOOP="" OPTYPE="add" PRAGMA="" RTLNAME="add_ln61_56_fu_3857_p2" SOURCE="ecal_cosmic_hls.cpp:61" STORAGESUBTYPE="" URAM="0" VARIABLE="add_ln61_56"/>
                <BindNode BINDTYPE="op" BRAM="0" BUNDLEDNAME="" DISPNAME="bind_op add" DSP="0" ID="" IMPL="fabric" LATENCY="0" LOOP="" OPTYPE="add" PRAGMA="" RTLNAME="add_ln61_57_fu_3903_p2" SOURCE="ecal_cosmic_hls.cpp:61" STORAGESUBTYPE="" URAM="0" VARIABLE="add_ln61_57"/>
                <BindNode BINDTYPE="op" BRAM="0" BUNDLEDNAME="" DISPNAME="bind_op add" DSP="0" ID="" IMPL="fabric" LATENCY="0" LOOP="" OPTYPE="add" PRAGMA="" RTLNAME="add_ln61_58_fu_3949_p2" SOURCE="ecal_cosmic_hls.cpp:61" STORAGESUBTYPE="" URAM="0" VARIABLE="add_ln61_58"/>
                <BindNode BINDTYPE="op" BRAM="0" BUNDLEDNAME="" DISPNAME="bind_op add" DSP="0" ID="" IMPL="fabric" LATENCY="0" LOOP="" OPTYPE="add" PRAGMA="" RTLNAME="add_ln61_59_fu_3995_p2" SOURCE="ecal_cosmic_hls.cpp:61" STORAGESUBTYPE="" URAM="0" VARIABLE="add_ln61_59"/>
                <BindNode BINDTYPE="op" BRAM="0" BUNDLEDNAME="" DISPNAME="bind_op add" DSP="0" ID="" IMPL="fabric" LATENCY="0" LOOP="" OPTYPE="add" PRAGMA="" RTLNAME="add_ln61_60_fu_4041_p2" SOURCE="ecal_cosmic_hls.cpp:61" STORAGESUBTYPE="" URAM="0" VARIABLE="add_ln61_60"/>
                <BindNode BINDTYPE="op" BRAM="0" BUNDLEDNAME="" DISPNAME="bind_op add" DSP="0" ID="" IMPL="fabric" LATENCY="0" LOOP="" OPTYPE="add" PRAGMA="" RTLNAME="add_ln61_61_fu_4087_p2" SOURCE="ecal_cosmic_hls.cpp:61" STORAGESUBTYPE="" URAM="0" VARIABLE="add_ln61_61"/>
                <BindNode BINDTYPE="op" BRAM="0" BUNDLEDNAME="" DISPNAME="bind_op add" DSP="0" ID="" IMPL="fabric" LATENCY="0" LOOP="" OPTYPE="add" PRAGMA="" RTLNAME="add_ln61_62_fu_4133_p2" SOURCE="ecal_cosmic_hls.cpp:61" STORAGESUBTYPE="" URAM="0" VARIABLE="add_ln61_62"/>
                <BindNode BINDTYPE="op" BRAM="0" BUNDLEDNAME="" DISPNAME="bind_op add" DSP="0" ID="" IMPL="fabric" LATENCY="0" LOOP="" OPTYPE="add" PRAGMA="" RTLNAME="add_ln61_63_fu_4271_p2" SOURCE="ecal_cosmic_hls.cpp:61" STORAGESUBTYPE="" URAM="0" VARIABLE="add_ln61_63"/>
                <BindNode BINDTYPE="op" BRAM="0" BUNDLEDNAME="" DISPNAME="bind_op add" DSP="0" ID="" IMPL="fabric" LATENCY="0" LOOP="" OPTYPE="add" PRAGMA="" RTLNAME="add_ln61_64_fu_4317_p2" SOURCE="ecal_cosmic_hls.cpp:61" STORAGESUBTYPE="" URAM="0" VARIABLE="add_ln61_64"/>
                <BindNode BINDTYPE="op" BRAM="0" BUNDLEDNAME="" DISPNAME="bind_op add" DSP="0" ID="" IMPL="fabric" LATENCY="0" LOOP="" OPTYPE="add" PRAGMA="" RTLNAME="add_ln61_65_fu_4363_p2" SOURCE="ecal_cosmic_hls.cpp:61" STORAGESUBTYPE="" URAM="0" VARIABLE="add_ln61_65"/>
                <BindNode BINDTYPE="op" BRAM="0" BUNDLEDNAME="" DISPNAME="bind_op add" DSP="0" ID="" IMPL="fabric" LATENCY="0" LOOP="" OPTYPE="add" PRAGMA="" RTLNAME="add_ln61_66_fu_4409_p2" SOURCE="ecal_cosmic_hls.cpp:61" STORAGESUBTYPE="" URAM="0" VARIABLE="add_ln61_66"/>
                <BindNode BINDTYPE="op" BRAM="0" BUNDLEDNAME="" DISPNAME="bind_op add" DSP="0" ID="" IMPL="fabric" LATENCY="0" LOOP="" OPTYPE="add" PRAGMA="" RTLNAME="add_ln61_67_fu_4455_p2" SOURCE="ecal_cosmic_hls.cpp:61" STORAGESUBTYPE="" URAM="0" VARIABLE="add_ln61_67"/>
                <BindNode BINDTYPE="op" BRAM="0" BUNDLEDNAME="" DISPNAME="bind_op add" DSP="0" ID="" IMPL="fabric" LATENCY="0" LOOP="" OPTYPE="add" PRAGMA="" RTLNAME="add_ln61_68_fu_4501_p2" SOURCE="ecal_cosmic_hls.cpp:61" STORAGESUBTYPE="" URAM="0" VARIABLE="add_ln61_68"/>
                <BindNode BINDTYPE="op" BRAM="0" BUNDLEDNAME="" DISPNAME="bind_op add" DSP="0" ID="" IMPL="fabric" LATENCY="0" LOOP="" OPTYPE="add" PRAGMA="" RTLNAME="add_ln61_69_fu_4547_p2" SOURCE="ecal_cosmic_hls.cpp:61" STORAGESUBTYPE="" URAM="0" VARIABLE="add_ln61_69"/>
            </BindNodes>
        </Module>
    </ModuleInformation>
    <FIFOInformation/>
    <UserConfigCommands>
        <config_rtl module_prefix="c2" reset="state"/>
    </UserConfigCommands>
    <Args>
        <Arg ArgName="hit_width" index="0" direction="in" srcType="ap_uint&lt;3&gt;" srcSize="8">
            <hwRefs>
                <hwRef type="port" interface="hit_width" name="hit_width" usage="data" direction="in"/>
            </hwRefs>
        </Arg>
        <Arg ArgName="row_threshold" index="1" direction="in" srcType="ap_uint&lt;4&gt;" srcSize="8">
            <hwRefs>
                <hwRef type="port" interface="row_threshold" name="row_threshold" usage="data" direction="in"/>
            </hwRefs>
        </Arg>
        <Arg ArgName="s_fadc_hits_vxs" index="2" direction="in" srcType="stream&lt;fadc_hits_vxs, 0&gt;&amp;" srcSize="320">
            <hwRefs>
                <hwRef type="interface" interface="s_fadc_hits_vxs" name="" usage="data" direction="in"/>
            </hwRefs>
        </Arg>
        <Arg ArgName="s_trigger_t" index="3" direction="out" srcType="stream&lt;trigger_t, 0&gt;&amp;" srcSize="8">
            <hwRefs>
                <hwRef type="interface" interface="s_trigger_t" name="" usage="data" direction="out"/>
            </hwRefs>
        </Arg>
    </Args>
    <Interfaces>
        <Interface InterfaceName="ap_clk" type="clock" busTypeName="clock" mode="slave">
            <busParams>
                <busParam busParamName="ASSOCIATED_RESET">ap_rst</busParam>
            </busParams>
            <portMaps>
                <portMap portMapName="ap_clk">CLK</portMap>
            </portMaps>
            <ports>
                <port>ap_clk</port>
            </ports>
        </Interface>
        <Interface InterfaceName="ap_rst" type="reset" busTypeName="reset" mode="slave">
            <busParams>
                <busParam busParamName="POLARITY">ACTIVE_HIGH</busParam>
            </busParams>
            <portMaps>
                <portMap portMapName="ap_rst">RST</portMap>
            </portMaps>
            <ports>
                <port>ap_rst</port>
            </ports>
        </Interface>
        <Interface InterfaceName="ap_ctrl" type="ap_ctrl" busTypeName="acc_handshake" mode="slave">
            <portMaps>
                <portMap portMapName="ap_start">start</portMap>
                <portMap portMapName="ap_done">done</portMap>
                <portMap portMapName="ap_idle">idle</portMap>
                <portMap portMapName="ap_ready">ready</portMap>
            </portMaps>
            <ports>
                <port>ap_done</port>
                <port>ap_idle</port>
                <port>ap_ready</port>
                <port>ap_start</port>
            </ports>
        </Interface>
        <Interface InterfaceName="s_fadc_hits_vxs" type="ap_fifo" busTypeName="acc_fifo_read" mode="master" dataWidth="160" portPrefix="s_fadc_hits_vxs_">
            <portMaps>
                <portMap portMapName="s_fadc_hits_vxs_dout">RD_DATA</portMap>
                <portMap portMapName="s_fadc_hits_vxs_empty_n">EMPTY_N</portMap>
                <portMap portMapName="s_fadc_hits_vxs_read">RD_EN</portMap>
            </portMaps>
            <ports>
                <port>s_fadc_hits_vxs_dout</port>
                <port>s_fadc_hits_vxs_empty_n</port>
                <port>s_fadc_hits_vxs_read</port>
            </ports>
            <constraints>
                <constraint constraint_type="pragma interface" mode="ap_fifo" register_option="0" argName="s_fadc_hits_vxs"/>
            </constraints>
        </Interface>
        <Interface InterfaceName="s_trigger_t" type="ap_fifo" busTypeName="acc_fifo_write" mode="master" dataWidth="8" portPrefix="s_trigger_t_">
            <portMaps>
                <portMap portMapName="s_trigger_t_din">WR_DATA</portMap>
                <portMap portMapName="s_trigger_t_full_n">FULL_N</portMap>
                <portMap portMapName="s_trigger_t_write">WR_EN</portMap>
            </portMaps>
            <ports>
                <port>s_trigger_t_din</port>
                <port>s_trigger_t_full_n</port>
                <port>s_trigger_t_write</port>
            </ports>
            <constraints>
                <constraint constraint_type="pragma interface" mode="ap_fifo" register_option="0" argName="s_trigger_t"/>
            </constraints>
        </Interface>
        <Interface InterfaceName="hit_width" type="data" busTypeName="data" protocol="ap_none" mode="slave" dataWidth="3">
            <portMaps>
                <portMap portMapName="hit_width">DATA</portMap>
            </portMaps>
            <ports>
                <port>hit_width</port>
            </ports>
            <constraints>
                <constraint constraint_type="pragma interface" mode="ap_none" register_option="0" argName="hit_width"/>
            </constraints>
        </Interface>
        <Interface InterfaceName="row_threshold" type="data" busTypeName="data" protocol="ap_none" mode="slave" dataWidth="4">
            <portMaps>
                <portMap portMapName="row_threshold">DATA</portMap>
            </portMaps>
            <ports>
                <port>row_threshold</port>
            </ports>
            <constraints>
                <constraint constraint_type="pragma interface" mode="ap_none" register_option="0" argName="row_threshold"/>
            </constraints>
        </Interface>
    </Interfaces>
    <ReportHWInterface>
        <section name="HW Interfaces" level="0">
            <item name="AP_FIFO">
                <table>
                    <keys size="3">Interface, Direction, Data Width</keys>
                    <column name="s_fadc_hits_vxs">out, 160</column>
                    <column name="s_trigger_t">out, 8</column>
                </table>
            </item>
            <item name="Other Ports">
                <table>
                    <keys size="4">Port, Mode, Direction, Bitwidth</keys>
                    <column name="hit_width">ap_none, in, 3</column>
                    <column name="row_threshold">ap_none, in, 4</column>
                </table>
            </item>
            <item name="TOP LEVEL CONTROL">
                <table>
                    <keys size="3">Interface, Type, Ports</keys>
                    <column name="ap_clk">clock, ap_clk</column>
                    <column name="ap_rst">reset, ap_rst</column>
                    <column name="ap_ctrl">ap_ctrl_hs, ap_done ap_idle ap_ready ap_start</column>
                </table>
            </item>
        </section>
    </ReportHWInterface>
    <ReportSWInterface>
        <section name="SW I/O Information" level="0">
            <item name="Top Function Arguments">
                <table>
                    <keys size="3">Argument, Direction, Datatype</keys>
                    <column name="hit_width">in, ap_uint&lt;3&gt;</column>
                    <column name="row_threshold">in, ap_uint&lt;4&gt;</column>
                    <column name="s_fadc_hits_vxs">in, stream&lt;fadc_hits_vxs 0&gt;&amp;</column>
                    <column name="s_trigger_t">out, stream&lt;trigger_t 0&gt;&amp;</column>
                </table>
            </item>
            <item name="SW-to-HW Mapping">
                <table>
                    <keys size="3">Argument, HW Interface, HW Type</keys>
                    <column name="hit_width">hit_width, port</column>
                    <column name="row_threshold">row_threshold, port</column>
                    <column name="s_fadc_hits_vxs">s_fadc_hits_vxs, interface</column>
                    <column name="s_trigger_t">s_trigger_t, interface</column>
                </table>
            </item>
        </section>
    </ReportSWInterface>
    <ResolutionUrl key="ZZZ">docs.xilinx.com/access/sources/dita/topic?Doc_Version=2023.2%20English&amp;url=ug1448-hls-guidance&amp;resourceid=ZZZ.html</ResolutionUrl>
    <PragmaReport>
        <Pragma type="interface" location="ecal_cosmic_hls.cpp:42" status="valid" parentFunction="ecal_cosmic_hls" variable="s_fadc_hits_vxs" isDirective="0" options="ap_fifo port=s_fadc_hits_vxs"/>
        <Pragma type="interface" location="ecal_cosmic_hls.cpp:43" status="valid" parentFunction="ecal_cosmic_hls" variable="s_trigger_t" isDirective="0" options="ap_fifo port=s_trigger_t"/>
        <Pragma type="pipeline" location="ecal_cosmic_hls.cpp:45" status="valid" parentFunction="ecal_cosmic_hls" variable="" isDirective="0" options="II=1 style=flp"/>
    </PragmaReport>
    <AutoPragmaReport>
        <AutoPragma type="array_partition" parentFunction="ecal_cosmic_hls" options="dim=1 type=complete  variable=_ZZ15ecal_cosmic_hls7ap_uintILi3EES_ILi4EERN3hls6streamI13fadc_hits_vxsLi0EEERNS3_I9trigger_tLi0EEEE16fadc_hits_stream" pragmaLocId="ecal_cosmic_hls.cpp:48:0" srcPragmaType="pipeline" srcPragmaLoc="ecal_cosmic_hls.cpp:45" srcPragmaSource="pragma" srcIsDirective="0" variable="ecal_cosmic_hls(ap_uint&lt;3&gt;, ap_uint&lt;4&gt;, hls::stream&lt;fadc_hits_vxs, 0&gt;&amp;, hls::stream&lt;trigger_t, 0&gt;&amp;)::fadc_hits_stream" varLoc=""/>
    </AutoPragmaReport>
</profile>

